LICENSE
MANIFEST.in
README.md
requirements.txt
setup.cfg
setup.py
chainer_mask_rcnn/__init__.py
chainer_mask_rcnn.egg-info/PKG-INFO
chainer_mask_rcnn.egg-info/SOURCES.txt
chainer_mask_rcnn.egg-info/dependency_links.txt
chainer_mask_rcnn.egg-info/requires.txt
chainer_mask_rcnn.egg-info/top_level.txt
chainer_mask_rcnn/datasets/__init__.py
chainer_mask_rcnn/datasets/coco.py
chainer_mask_rcnn/datasets/concat_examples.py
chainer_mask_rcnn/datasets/indexing_dataset.py
chainer_mask_rcnn/datasets/mask_rcnn.py
chainer_mask_rcnn/datasets/transforms.py
chainer_mask_rcnn/datasets/view_dataset.py
chainer_mask_rcnn/datasets/voc/__init__.py
chainer_mask_rcnn/datasets/voc/sbd.py
chainer_mask_rcnn/datasets/voc/voc.py
chainer_mask_rcnn/datasets/voc/data/VOCdevkit/VOCSDS/ImageSets/Main/README
chainer_mask_rcnn/datasets/voc/data/VOCdevkit/VOCSDS/ImageSets/Main/train.txt
chainer_mask_rcnn/datasets/voc/data/VOCdevkit/VOCSDS/ImageSets/Main/val.txt
chainer_mask_rcnn/extensions/__init__.py
chainer_mask_rcnn/extensions/instance_segmentation_coco_evaluator.py
chainer_mask_rcnn/extensions/instance_segmentation_vis_report.py
chainer_mask_rcnn/extensions/instance_segmentation_voc_evaluator.py
chainer_mask_rcnn/functions/__init__.py
chainer_mask_rcnn/functions/affine_channel_2d.py
chainer_mask_rcnn/functions/crop_and_resize.py
chainer_mask_rcnn/functions/roi_align_2d.py
chainer_mask_rcnn/functions/roi_pooling_2d.py
chainer_mask_rcnn/links/__init__.py
chainer_mask_rcnn/links/affine_channel_2d.py
chainer_mask_rcnn/models/__init__.py
chainer_mask_rcnn/models/mask_rcnn.py
chainer_mask_rcnn/models/mask_rcnn_resnet.py
chainer_mask_rcnn/models/mask_rcnn_train_chain.py
chainer_mask_rcnn/models/region_proposal_network.py
chainer_mask_rcnn/models/resnet_extractor.py
chainer_mask_rcnn/models/utils/__init__.py
chainer_mask_rcnn/models/utils/proposal_target_creator.py
chainer_mask_rcnn/utils/__init__.py
chainer_mask_rcnn/utils/_itertools.py
chainer_mask_rcnn/utils/_shutil.py
chainer_mask_rcnn/utils/geometry.py
chainer_mask_rcnn/utils/visualizations.py
chainer_mask_rcnn/utils/evaluations/__init__.py
chainer_mask_rcnn/utils/evaluations/eval_instance_segmentation_coco.py
